<?xml version="1.0" encoding="UTF-8" ?>


<Behavs>
  <Behav ID="BehavFlow00">
    <BehavList>BehavReadingMenu,BehavWaitForOrder,BehavWaitForFood,BehavEating,BehavWaitForCheck,BehavNotifyLeave,BehavAllergyAttack,BehavSaved,BehavHospital</BehavList>
  </Behav>
  <Behav ID="BehavFlow01">
    <BehavList>BehavReadingMenu,BehavWaitForOrder,BehavWaitForFood,BehavEating,BehavWaitForCheck,BehavEaterNotifyLeave,BehavAllergyAttack,BehavSaved,BehavHospital,BehavNotifyLeave</BehavList>
  </Behav>
  <Behav ID="BehavFlow01">
    <BehavList>BehavReadingMenu,BehavWaitForOrder,BehavWaitForFood,BehavEating,BehavWaitForCheck,BehavTableSmasherNotifyLeave,BehavAllergyAttack,BehavSaved,BehavHospital,BehavNotifyLeave</BehavList>
  </Behav>
</Behavs>
